pretix_uic_barcode/__init__.py
pretix_uic_barcode/api.py
pretix_uic_barcode/apps.py
pretix_uic_barcode/barcode.py
pretix_uic_barcode/elements.py
pretix_uic_barcode/event_settings.py
pretix_uic_barcode/forms.py
pretix_uic_barcode/gwallet.py
pretix_uic_barcode/models.py
pretix_uic_barcode/pkpass.py
pretix_uic_barcode/secrets.py
pretix_uic_barcode/signals.py
pretix_uic_barcode/ticket_output.py
pretix_uic_barcode/ticket_output_apple_wallet.py
pretix_uic_barcode/ticket_output_google_wallet.py
pretix_uic_barcode/ticket_output_pdf.py
pretix_uic_barcode/ticket_output_raw.py
pretix_uic_barcode/urls.py
pretix_uic_barcode/utils.py
pretix_uic_barcode/vas.py
pretix_uic_barcode/views.py
pretix_uic_barcode/asn1/uicBarcodeHeader_v2.0.1.asn
pretix_uic_barcode/asn1/uicPretix.asn
pretix_uic_barcode/asn1/uicTotp.asn
pretix_uic_barcode/asn1/vasData.asn
pretix_uic_barcode/locale/de/LC_MESSAGES/django.mo
pretix_uic_barcode/locale/de/LC_MESSAGES/django.po
pretix_uic_barcode/locale/de_Informal/.gitkeep
pretix_uic_barcode/locale/de_Informal/LC_MESSAGES/django.mo
pretix_uic_barcode/locale/de_Informal/LC_MESSAGES/django.po
pretix_uic_barcode/migrations/0001_squashed_0003_applewalletpass_order_position.py
pretix_uic_barcode/migrations/0004_orderpositiontotp.py
pretix_uic_barcode/migrations/0005_googleeventlog.py
pretix_uic_barcode/migrations/__init__.py
pretix_uic_barcode/static/pretix_uic_barcode/icon.png
pretix_uic_barcode/static/pretix_uic_barcode/wwdrg4.pem
pretix_uic_barcode/templates/pretix_uic_barcode/.gitkeep
pretix_uic_barcode/templates/pretix_uic_barcode/settings.html
pretix_uic_barcode-1.7.10.dist-info/licenses/LICENSE.md
pretix_uic_barcode-1.7.10.dist-info/METADATA
pretix_uic_barcode-1.7.10.dist-info/WHEEL
pretix_uic_barcode-1.7.10.dist-info/entry_points.txt
pretix_uic_barcode-1.7.10.dist-info/top_level.txt
pretix_uic_barcode-1.7.10.dist-info/RECORD
