Metadata-Version: 2.4
Name: pretix-uic-barcode
Version: 1.7.10
Summary: UIC Barcodes for Pretix tickets
Author-email: Q Misell <q@magicalcodewit.ch>
Maintainer-email: Q Misell <q@magicalcodewit.ch>
License-Expression: EUPL-1.2
Project-URL: homepage, https://github.com/TheEnbyperor/pretix-uic-barcode
Project-URL: repository, https://github.com/TheEnbyperor/pretix-uic-barcode
Keywords: pretix
License-File: LICENSE.md
Requires-Dist: asn1tools
Requires-Dist: asn1crypto
Requires-Dist: base45
Requires-Dist: ber-tlv
Requires-Dist: aztec-code-generator
Requires-Dist: niquests
Requires-Dist: cryptography
Requires-Dist: idna
Requires-Dist: google-api-python-client
Requires-Dist: drf-base64-binaryfield
Dynamic: license-file
